cybersectk/__init__.py
cybersectk/iot.py
cybersectk/malware.py
cybersectk/wiot.py
cybersectk-1.0.dist-info/LICENSE
cybersectk-1.0.dist-info/METADATA
cybersectk-1.0.dist-info/WHEEL
cybersectk-1.0.dist-info/top_level.txt
cybersectk-1.0.dist-info/RECORD
