Metadata-Version: 2.1
Name: cybersectk
Version: 1.0
Summary: Fork of cybersectk, a library for Machine Learning CyberSec feature extraction. Original author: SumendraBSingh
Home-page: https://github.com/unspezifische/CyberSecTK
Author: Unspezifische
Author-email: unspezifische@gmail.com
License: MIT
Classifier: Development Status :: 4 - Beta
Classifier: Programming Language :: Python :: 3.11
Classifier: Topic :: Software Development :: Libraries :: Python Modules
Requires-Python: >=3.11
License-File: LICENSE
Requires-Dist: scapy
Requires-Dist: numpy
Requires-Dist: scikit-learn
